[[{"__type__":"cc.Prefab","_name":"order_jelly_s","data":{"__id__":1},"asyncLoadAssets":null},{"__type__":"cc.Node","_name":"order_jelly_s","_components":[{"__type__":"cc.Sprite","node":{"__id__":1},"_spriteFrame":{"__uuid__":"f2ahqae6hBYLZ33f+JXKod"}}],"_prefab":{"__type__":"cc.PrefabInfo","root":{"__id__":1},"asset":{"__id__":0},"fileId":"94QvpEikhPO5d1+H4CC9kw"},"_contentSize":{"__type__":"cc.Size","width":53,"height":55}}],{"__type__":"cc.SpriteFrame","content":{"name":"order_jelly_s","texture":"1606ba8a","rect":[686,572,53,55],"offset":[0.5,-0.5],"originalSize":[68,68]}}]