{"__type__":"cc.SpriteAtlas","_spriteFrames":{"0":{"__uuid__":"5e5Sl4725OCqEosytIglut"},"1":{"__uuid__":"14mXuGYCxPD4GZ1TMtCesq"},"12":{"__uuid__":"a1QUiiVfdCjpaRRXvgPVhv"},"13":{"__uuid__":"a1ZxyLZ7ZCc7IBFxxK0p8t"},"14":{"__uuid__":"5fX5Pr/fdCT6AqSVpWr6ts"},"15":{"__uuid__":"423xcCj2lDj4mhqmQgwZwp"},"16":{"__uuid__":"dcVZoI2GZJY4JJET0l3REZ"},"17":{"__uuid__":"3eA3SDPVtG6qTsYXnk7B2N"},"18":{"__uuid__":"d2WGEMGgdKMp/biuahIF3h"},"19":{"__uuid__":"1aS52IvaFHdL3UwrOw2mN2"},"20":{"__uuid__":"e82mOUFvFKkrpI67ekfdai"},"21":{"__uuid__":"58hQ1XmkBCqobiRuSAwuR5"},"22":{"__uuid__":"03LGZki4lMM6Vcs+ehADuO"},"23":{"__uuid__":"5dH8EICY1DjpJJMLFF7Qt5"},"24":{"__uuid__":"5ci+hhsHNEJKe/VAVHNUbY"},"25":{"__uuid__":"5c5qVF6+NAh6TZBx+P5gUp"}}}